[{
  "_id": {
    "$oid": "6327ad109c6ea1d38a90e3fc"
  },
  "user": {
    "$oid": "6326e07f8cccc808c6ea29bc"
  },
  "amount": 69,
  "paymentMethod": "card",
  "orders": [
    {
      "$oid": "6326f1a64fe66eaa721bb9e1"
    }
  ],
  "createdAt": {
    "$date": {
      "$numberLong": "1663544592903"
    }
  },
  "updatedAt": {
    "$date": {
      "$numberLong": "1663544592903"
    }
  },
  "__v": 0
},{
  "_id": {
    "$oid": "6327ad9b59e14e7017b3d945"
  },
  "user": {
    "$oid": "6326e07f8cccc808c6ea29bc"
  },
  "amount": 69,
  "paymentMethod": "card",
  "orders": [
    {
      "$oid": "6327ad99f59606babcf72205"
    }
  ],
  "createdAt": {
    "$date": {
      "$numberLong": "1663544731361"
    }
  },
  "updatedAt": {
    "$date": {
      "$numberLong": "1663544731361"
    }
  },
  "__v": 0
},{
  "_id": {
    "$oid": "6327ae481f626a757131d929"
  },
  "user": {
    "$oid": "6326e07f8cccc808c6ea29bc"
  },
  "amount": 69,
  "paymentMethod": "card",
  "orders": [
    {
      "$oid": "6327ae459dc38b63e1296b92"
    }
  ],
  "createdAt": {
    "$date": {
      "$numberLong": "1663544904613"
    }
  },
  "updatedAt": {
    "$date": {
      "$numberLong": "1663544904613"
    }
  },
  "__v": 0
},{
  "_id": {
    "$oid": "6327aed2c3ceddaee72c3ac2"
  },
  "user": {
    "$oid": "6326e07f8cccc808c6ea29bc"
  },
  "amount": 69,
  "paymentMethod": "card",
  "orders": [
    {
      "$oid": "6327aecf616bdb129f67eabb"
    }
  ],
  "createdAt": {
    "$date": {
      "$numberLong": "1663545042234"
    }
  },
  "updatedAt": {
    "$date": {
      "$numberLong": "1663545042234"
    }
  },
  "__v": 0
},{
  "_id": {
    "$oid": "6327afa8132a6b432eb860a8"
  },
  "user": {
    "$oid": "6326e07f8cccc808c6ea29bc"
  },
  "amount": 69,
  "paymentMethod": "card",
  "orders": [
    {
      "$oid": "6327afa648cb569754678da5"
    }
  ],
  "createdAt": {
    "$date": {
      "$numberLong": "1663545256387"
    }
  },
  "updatedAt": {
    "$date": {
      "$numberLong": "1663545256387"
    }
  },
  "__v": 0
},{
  "_id": {
    "$oid": "6327aff4f57f99dd181d0f55"
  },
  "user": {
    "$oid": "6326e07f8cccc808c6ea29bc"
  },
  "amount": 69,
  "paymentMethod": "card",
  "orders": [
    {
      "$oid": "6327aff281b9c04ed0c7d3ae"
    }
  ],
  "createdAt": {
    "$date": {
      "$numberLong": "1663545332243"
    }
  },
  "updatedAt": {
    "$date": {
      "$numberLong": "1663545332243"
    }
  },
  "__v": 0
},{
  "_id": {
    "$oid": "6327b0891cf033fa84e1d9bb"
  },
  "user": {
    "$oid": "6326e07f8cccc808c6ea29bc"
  },
  "amount": 69,
  "paymentMethod": "card",
  "orders": [
    {
      "$oid": "6327b08429d292a2735bec37"
    }
  ],
  "createdAt": {
    "$date": {
      "$numberLong": "1663545481414"
    }
  },
  "updatedAt": {
    "$date": {
      "$numberLong": "1663545481414"
    }
  },
  "__v": 0
},{
  "_id": {
    "$oid": "6327b0cb2f490df107195791"
  },
  "user": {
    "$oid": "6326e07f8cccc808c6ea29bc"
  },
  "amount": 69,
  "paymentMethod": "card",
  "orders": [
    {
      "$oid": "6327b0c8809536b2179ca753"
    }
  ],
  "createdAt": {
    "$date": {
      "$numberLong": "1663545547616"
    }
  },
  "updatedAt": {
    "$date": {
      "$numberLong": "1663545547616"
    }
  },
  "__v": 0
},{
  "_id": {
    "$oid": "6327b1208f6cc8141dfe08cf"
  },
  "user": {
    "$oid": "6326e07f8cccc808c6ea29bc"
  },
  "amount": 69,
  "paymentMethod": "card",
  "orders": [
    {
      "$oid": "6327b11d3a88f5be157efec1"
    }
  ],
  "createdAt": {
    "$date": {
      "$numberLong": "1663545632150"
    }
  },
  "updatedAt": {
    "$date": {
      "$numberLong": "1663545632150"
    }
  },
  "__v": 0
},{
  "_id": {
    "$oid": "6327b19ee0d6c0e4b6c0fc78"
  },
  "user": {
    "$oid": "6326e07f8cccc808c6ea29bc"
  },
  "amount": 69,
  "paymentMethod": "card",
  "orders": [
    {
      "$oid": "6327b19c46d11d935029b17c"
    }
  ],
  "createdAt": {
    "$date": {
      "$numberLong": "1663545758729"
    }
  },
  "updatedAt": {
    "$date": {
      "$numberLong": "1663545758729"
    }
  },
  "__v": 0
},{
  "_id": {
    "$oid": "6327b22743651c4b8d6c8839"
  },
  "user": {
    "$oid": "6326e07f8cccc808c6ea29bc"
  },
  "amount": 69,
  "paymentMethod": "card",
  "orders": [
    {
      "$oid": "6327b2257bff558a9ac74d33"
    }
  ],
  "createdAt": {
    "$date": {
      "$numberLong": "1663545895040"
    }
  },
  "updatedAt": {
    "$date": {
      "$numberLong": "1663545895040"
    }
  },
  "__v": 0
},{
  "_id": {
    "$oid": "6327b2dd02bbf0de576bc3bc"
  },
  "user": {
    "$oid": "6326e07f8cccc808c6ea29bc"
  },
  "amount": 69,
  "paymentMethod": "card",
  "orders": [
    {
      "$oid": "6327b2d9a55e6a5c30a3b8eb"
    }
  ],
  "createdAt": {
    "$date": {
      "$numberLong": "1663546077437"
    }
  },
  "updatedAt": {
    "$date": {
      "$numberLong": "1663546077437"
    }
  },
  "__v": 0
},{
  "_id": {
    "$oid": "6327b32f22405663aac64a27"
  },
  "user": {
    "$oid": "6326e07f8cccc808c6ea29bc"
  },
  "amount": 69,
  "paymentMethod": "card",
  "orders": [
    {
      "$oid": "6327b32ceb3fd6910c561b34"
    }
  ],
  "createdAt": {
    "$date": {
      "$numberLong": "1663546159086"
    }
  },
  "updatedAt": {
    "$date": {
      "$numberLong": "1663546159086"
    }
  },
  "__v": 0
},{
  "_id": {
    "$oid": "6327b5eead8d760b374fb596"
  },
  "user": {
    "$oid": "6326e07f8cccc808c6ea29bc"
  },
  "amount": 23,
  "paymentMethod": "card",
  "orders": [
    {
      "$oid": "6327b5ec8c3e61ce198af221"
    }
  ],
  "createdAt": {
    "$date": {
      "$numberLong": "1663546862882"
    }
  },
  "updatedAt": {
    "$date": {
      "$numberLong": "1663546862882"
    }
  },
  "__v": 0
},{
  "_id": {
    "$oid": "6327b81a4ee1df39943fbf97"
  },
  "user": {
    "$oid": "6326e07f8cccc808c6ea29bc"
  },
  "amount": 138,
  "paymentMethod": "card",
  "orders": [
    {
      "$oid": "6327b81738b9ab44145c5242"
    }
  ],
  "createdAt": {
    "$date": {
      "$numberLong": "1663547418436"
    }
  },
  "updatedAt": {
    "$date": {
      "$numberLong": "1663547418437"
    }
  },
  "__v": 0
},{
  "_id": {
    "$oid": "6327b8a8d21ce98d40ae1733"
  },
  "user": {
    "$oid": "6326e07f8cccc808c6ea29bc"
  },
  "amount": 138,
  "paymentMethod": "card",
  "orders": [
    {
      "$oid": "6327b8a6b90e028ec9d3e754"
    }
  ],
  "createdAt": {
    "$date": {
      "$numberLong": "1663547560903"
    }
  },
  "updatedAt": {
    "$date": {
      "$numberLong": "1663547560903"
    }
  },
  "__v": 0
},{
  "_id": {
    "$oid": "6327b8eb5fe85d6359ada77f"
  },
  "user": {
    "$oid": "6326e07f8cccc808c6ea29bc"
  },
  "amount": 138,
  "paymentMethod": "card",
  "orders": [
    {
      "$oid": "6327b8e89c6e62f3bfa56e6a"
    }
  ],
  "createdAt": {
    "$date": {
      "$numberLong": "1663547627984"
    }
  },
  "updatedAt": {
    "$date": {
      "$numberLong": "1663547627984"
    }
  },
  "__v": 0
},{
  "_id": {
    "$oid": "6327d4c7e7db1ef4b18588fe"
  },
  "user": {
    "$oid": "6326e07f8cccc808c6ea29bc"
  },
  "amount": {
    "$numberLong": "788696869868"
  },
  "paymentMethod": "card",
  "orders": [],
  "createdAt": {
    "$date": {
      "$numberLong": "1663554759147"
    }
  },
  "updatedAt": {
    "$date": {
      "$numberLong": "1663554759147"
    }
  },
  "__v": 0
},{
  "_id": {
    "$oid": "6327d4eaa3d0eb4e88c1e39a"
  },
  "user": {
    "$oid": "6326e07f8cccc808c6ea29bc"
  },
  "amount": 50000,
  "paymentMethod": "mobile",
  "orders": [],
  "createdAt": {
    "$date": {
      "$numberLong": "1663554794990"
    }
  },
  "updatedAt": {
    "$date": {
      "$numberLong": "1663554794990"
    }
  },
  "__v": 0
},{
  "_id": {
    "$oid": "6327d552a3d0eb4e88c1e39c"
  },
  "user": {
    "$oid": "6326e07f8cccc808c6ea29bc"
  },
  "amount": 50000,
  "paymentMethod": "mobile",
  "mobile": "0711008769",
  "orders": [],
  "createdAt": {
    "$date": {
      "$numberLong": "1663554898822"
    }
  },
  "updatedAt": {
    "$date": {
      "$numberLong": "1663554898822"
    }
  },
  "__v": 0
},{
  "_id": {
    "$oid": "6327ee862944714c7ba704a6"
  },
  "user": {
    "$oid": "6326e07f8cccc808c6ea29bc"
  },
  "amount": 114,
  "paymentMethod": "card",
  "orders": [
    {
      "$oid": "6327ee84bf0387a78fc44c71"
    }
  ],
  "createdAt": {
    "$date": {
      "$numberLong": "1663561350824"
    }
  },
  "updatedAt": {
    "$date": {
      "$numberLong": "1663561350825"
    }
  },
  "__v": 0
},{
  "_id": {
    "$oid": "6327eef52944714c7ba704a8"
  },
  "user": {
    "$oid": "6326e07f8cccc808c6ea29bc"
  },
  "amount": 23,
  "paymentMethod": "card",
  "orders": [
    {
      "$oid": "6327eef3bf0387a78fc44c7a"
    }
  ],
  "createdAt": {
    "$date": {
      "$numberLong": "1663561461224"
    }
  },
  "updatedAt": {
    "$date": {
      "$numberLong": "1663561461224"
    }
  },
  "__v": 0
},{
  "_id": {
    "$oid": "6327efb02944714c7ba704aa"
  },
  "user": {
    "$oid": "6326e07f8cccc808c6ea29bc"
  },
  "amount": 19,
  "paymentMethod": "card",
  "orders": [
    {
      "$oid": "6327ef9dbf0387a78fc44c83"
    }
  ],
  "createdAt": {
    "$date": {
      "$numberLong": "1663561648718"
    }
  },
  "updatedAt": {
    "$date": {
      "$numberLong": "1663561648719"
    }
  },
  "__v": 0
},{
  "_id": {
    "$oid": "6327efe22944714c7ba704ac"
  },
  "user": {
    "$oid": "6326e07f8cccc808c6ea29bc"
  },
  "amount": 19,
  "paymentMethod": "card",
  "orders": [
    {
      "$oid": "6327efdfbf0387a78fc44c8c"
    }
  ],
  "createdAt": {
    "$date": {
      "$numberLong": "1663561698039"
    }
  },
  "updatedAt": {
    "$date": {
      "$numberLong": "1663561698039"
    }
  },
  "__v": 0
},{
  "_id": {
    "$oid": "6327f0a62944714c7ba704ae"
  },
  "user": {
    "$oid": "6326e07f8cccc808c6ea29bc"
  },
  "amount": 76,
  "paymentMethod": "card",
  "orders": [
    {
      "$oid": "6327f0a4bf0387a78fc44c95"
    }
  ],
  "createdAt": {
    "$date": {
      "$numberLong": "1663561894357"
    }
  },
  "updatedAt": {
    "$date": {
      "$numberLong": "1663561894357"
    }
  },
  "__v": 0
},{
  "_id": {
    "$oid": "6327f12a2944714c7ba704b0"
  },
  "user": {
    "$oid": "6326e07f8cccc808c6ea29bc"
  },
  "amount": 172,
  "paymentMethod": "card",
  "orders": [
    {
      "$oid": "6327f127bf0387a78fc44c9e"
    }
  ],
  "createdAt": {
    "$date": {
      "$numberLong": "1663562026711"
    }
  },
  "updatedAt": {
    "$date": {
      "$numberLong": "1663562026711"
    }
  },
  "__v": 0
},{
  "_id": {
    "$oid": "6327f35ce6d0db5936060fda"
  },
  "user": {
    "$oid": "631b2c2d4b8c7fc988a49a73"
  },
  "amount": 69,
  "paymentMethod": "card",
  "orders": [
    {
      "$oid": "6327f35c6a5478ca13fc4844"
    }
  ],
  "createdAt": {
    "$date": {
      "$numberLong": "1663562588893"
    }
  },
  "updatedAt": {
    "$date": {
      "$numberLong": "1663562588893"
    }
  },
  "__v": 0
},{
  "_id": {
    "$oid": "6327f8b16a55c273a438e6ba"
  },
  "user": {
    "$oid": "631b2c2d4b8c7fc988a49a75"
  },
  "amount": 69,
  "paymentMethod": "card",
  "orders": [
    {
      "$oid": "6327f8b0817d18735482a9f4"
    }
  ],
  "createdAt": {
    "$date": {
      "$numberLong": "1663563953632"
    }
  },
  "updatedAt": {
    "$date": {
      "$numberLong": "1663563953632"
    }
  },
  "__v": 0
},{
  "_id": {
    "$oid": "6327f9fe6a55c273a438e6bc"
  },
  "user": {
    "$oid": "631b2c2d4b8c7fc988a49a75"
  },
  "amount": 23,
  "paymentMethod": "card",
  "orders": [
    {
      "$oid": "6327f9fe817d18735482aa02"
    }
  ],
  "createdAt": {
    "$date": {
      "$numberLong": "1663564286914"
    }
  },
  "updatedAt": {
    "$date": {
      "$numberLong": "1663564286914"
    }
  },
  "__v": 0
},{
  "_id": {
    "$oid": "6327fb6a6a55c273a438e6be"
  },
  "user": {
    "$oid": "631b2c2d4b8c7fc988a49a75"
  },
  "amount": 19,
  "paymentMethod": "card",
  "orders": [
    {
      "$oid": "6327fb69817d18735482aa0b"
    }
  ],
  "createdAt": {
    "$date": {
      "$numberLong": "1663564650019"
    }
  },
  "updatedAt": {
    "$date": {
      "$numberLong": "1663564650019"
    }
  },
  "__v": 0
},{
  "_id": {
    "$oid": "6327fbaf6a55c273a438e6c0"
  },
  "user": {
    "$oid": "631b2c2d4b8c7fc988a49a75"
  },
  "amount": 76,
  "paymentMethod": "card",
  "orders": [
    {
      "$oid": "6327fbae817d18735482aa14"
    }
  ],
  "createdAt": {
    "$date": {
      "$numberLong": "1663564719757"
    }
  },
  "updatedAt": {
    "$date": {
      "$numberLong": "1663564719757"
    }
  },
  "__v": 0
},{
  "_id": {
    "$oid": "6327fc1c6a55c273a438e6c2"
  },
  "user": {
    "$oid": "631b2c2d4b8c7fc988a49a75"
  },
  "amount": 23,
  "paymentMethod": "card",
  "orders": [
    {
      "$oid": "6327fc1b817d18735482aa1d"
    }
  ],
  "createdAt": {
    "$date": {
      "$numberLong": "1663564828273"
    }
  },
  "updatedAt": {
    "$date": {
      "$numberLong": "1663564828273"
    }
  },
  "__v": 0
},{
  "_id": {
    "$oid": "635a313200c32b4921900fe0"
  },
  "user": {
    "$oid": "6326e07f8cccc808c6ea29bc"
  },
  "amount": 50000,
  "paymentMethod": "mobile",
  "mobile": "0711008769",
  "orders": [],
  "createdAt": {
    "$date": {
      "$numberLong": "1666855218329"
    }
  },
  "updatedAt": {
    "$date": {
      "$numberLong": "1666855218329"
    }
  },
  "__v": 0
},{
  "_id": {
    "$oid": "635b76b5a26909b1168f4f2f"
  },
  "user": {
    "$oid": "631b2c2d4b8c7fc988a49a73"
  },
  "amount": 308,
  "paymentMethod": "card",
  "orders": [
    {
      "$oid": "635b76b3ac8f5b6171bf6696"
    }
  ],
  "createdAt": {
    "$date": {
      "$numberLong": "1666938549315"
    }
  },
  "updatedAt": {
    "$date": {
      "$numberLong": "1666938549315"
    }
  },
  "__v": 0
},{
  "_id": {
    "$oid": "635b797f4a17d4b937e170a4"
  },
  "user": {
    "$oid": "631b2c2d4b8c7fc988a49a73"
  },
  "amount": 308,
  "paymentMethod": "card",
  "orders": [
    {
      "$oid": "635b797fccfb27f112414b8a"
    }
  ],
  "createdAt": {
    "$date": {
      "$numberLong": "1666939263886"
    }
  },
  "updatedAt": {
    "$date": {
      "$numberLong": "1666939263886"
    }
  },
  "__v": 0
},{
  "_id": {
    "$oid": "635b79d2d9c39ff6ccc2ca9c"
  },
  "user": {
    "$oid": "631b2c2d4b8c7fc988a49a73"
  },
  "amount": 331,
  "paymentMethod": "card",
  "orders": [
    {
      "$oid": "635b79d265ed5d0abf54df93"
    }
  ],
  "createdAt": {
    "$date": {
      "$numberLong": "1666939346591"
    }
  },
  "updatedAt": {
    "$date": {
      "$numberLong": "1666939346591"
    }
  },
  "__v": 0
},{
  "_id": {
    "$oid": "635b7af42af84e3528b662bb"
  },
  "user": {
    "$oid": "631b2c2d4b8c7fc988a49a73"
  },
  "amount": 55,
  "paymentMethod": "card",
  "orders": [
    {
      "$oid": "635b7af2a5e00010b2485cd6"
    }
  ],
  "createdAt": {
    "$date": {
      "$numberLong": "1666939636075"
    }
  },
  "updatedAt": {
    "$date": {
      "$numberLong": "1666939636075"
    }
  },
  "__v": 0
},{
  "_id": {
    "$oid": "635b7b9f0d05a6507e0650e9"
  },
  "user": {
    "$oid": "631b2c2d4b8c7fc988a49a73"
  },
  "amount": 55,
  "paymentMethod": "card",
  "orders": [
    {
      "$oid": "635b7b9c45a2f4b46185c157"
    }
  ],
  "createdAt": {
    "$date": {
      "$numberLong": "1666939807364"
    }
  },
  "updatedAt": {
    "$date": {
      "$numberLong": "1666939807365"
    }
  },
  "__v": 0
},{
  "_id": {
    "$oid": "635b7e1051df0103e5ea9988"
  },
  "user": {
    "$oid": "631b2c2d4b8c7fc988a49a73"
  },
  "amount": 69,
  "paymentMethod": "card",
  "orders": [
    {
      "$oid": "635b7e0f39dd2361c6578cbd"
    }
  ],
  "createdAt": {
    "$date": {
      "$numberLong": "1666940432713"
    }
  },
  "updatedAt": {
    "$date": {
      "$numberLong": "1666940432714"
    }
  },
  "__v": 0
},{
  "_id": {
    "$oid": "635b7e69edde004657fdb43a"
  },
  "user": {
    "$oid": "631b2c2d4b8c7fc988a49a73"
  },
  "amount": 69,
  "paymentMethod": "card",
  "orders": [
    {
      "$oid": "635b7e688aa2533bc823b6b8"
    }
  ],
  "createdAt": {
    "$date": {
      "$numberLong": "1666940521058"
    }
  },
  "updatedAt": {
    "$date": {
      "$numberLong": "1666940521058"
    }
  },
  "__v": 0
},{
  "_id": {
    "$oid": "635b8179b6373c1465449996"
  },
  "user": {
    "$oid": "631b2c2d4b8c7fc988a49a73"
  },
  "amount": 69,
  "paymentMethod": "card",
  "orders": [
    {
      "$oid": "635b8177d01a17a310ad8dad"
    }
  ],
  "createdAt": {
    "$date": {
      "$numberLong": "1666941305941"
    }
  },
  "updatedAt": {
    "$date": {
      "$numberLong": "1666941305941"
    }
  },
  "__v": 0
},{
  "_id": {
    "$oid": "635b8248e9252c0db9df4ccb"
  },
  "user": {
    "$oid": "631b2c2d4b8c7fc988a49a73"
  },
  "amount": 50,
  "paymentMethod": "card",
  "orders": [
    {
      "$oid": "635b82472dc1d99f7531e275"
    }
  ],
  "createdAt": {
    "$date": {
      "$numberLong": "1666941512392"
    }
  },
  "updatedAt": {
    "$date": {
      "$numberLong": "1666941512392"
    }
  },
  "__v": 0
},{
  "_id": {
    "$oid": "635b82fad7d972c95f6bcc9a"
  },
  "user": {
    "$oid": "631b2c2d4b8c7fc988a49a73"
  },
  "amount": 73,
  "paymentMethod": "card",
  "orders": [],
  "createdAt": {
    "$date": {
      "$numberLong": "1666941690306"
    }
  },
  "updatedAt": {
    "$date": {
      "$numberLong": "1666941690306"
    }
  },
  "__v": 0
},{
  "_id": {
    "$oid": "635b837dd7d972c95f6bcc9c"
  },
  "user": {
    "$oid": "631b2c2d4b8c7fc988a49a73"
  },
  "amount": 42,
  "paymentMethod": "card",
  "orders": [],
  "createdAt": {
    "$date": {
      "$numberLong": "1666941821839"
    }
  },
  "updatedAt": {
    "$date": {
      "$numberLong": "1666941821839"
    }
  },
  "__v": 0
},{
  "_id": {
    "$oid": "635b850791e5dc87a240a113"
  },
  "user": {
    "$oid": "631b2c2d4b8c7fc988a49a73"
  },
  "amount": 42,
  "paymentMethod": "card",
  "orders": [],
  "createdAt": {
    "$date": {
      "$numberLong": "1666942215351"
    }
  },
  "updatedAt": {
    "$date": {
      "$numberLong": "1666942215351"
    }
  },
  "__v": 0
},{
  "_id": {
    "$oid": "635b864029d89ce617019df7"
  },
  "user": {
    "$oid": "631b2c2d4b8c7fc988a49a73"
  },
  "amount": 42,
  "paymentMethod": "card",
  "orders": [],
  "createdAt": {
    "$date": {
      "$numberLong": "1666942528979"
    }
  },
  "updatedAt": {
    "$date": {
      "$numberLong": "1666942528979"
    }
  },
  "__v": 0
},{
  "_id": {
    "$oid": "635b86cf7a80cd26d4afd5d3"
  },
  "user": {
    "$oid": "631b2c2d4b8c7fc988a49a73"
  },
  "amount": 42,
  "paymentMethod": "card",
  "orders": [],
  "createdAt": {
    "$date": {
      "$numberLong": "1666942671068"
    }
  },
  "updatedAt": {
    "$date": {
      "$numberLong": "1666942671068"
    }
  },
  "__v": 0
},{
  "_id": {
    "$oid": "635b8709bd007415cc096856"
  },
  "user": {
    "$oid": "631b2c2d4b8c7fc988a49a73"
  },
  "amount": 42,
  "paymentMethod": "card",
  "orders": [],
  "createdAt": {
    "$date": {
      "$numberLong": "1666942729273"
    }
  },
  "updatedAt": {
    "$date": {
      "$numberLong": "1666942729273"
    }
  },
  "__v": 0
},{
  "_id": {
    "$oid": "635b8779bc3db8193a8ae50b"
  },
  "user": {
    "$oid": "631b2c2d4b8c7fc988a49a73"
  },
  "amount": 42,
  "paymentMethod": "card",
  "orders": [],
  "createdAt": {
    "$date": {
      "$numberLong": "1666942841155"
    }
  },
  "updatedAt": {
    "$date": {
      "$numberLong": "1666942841155"
    }
  },
  "__v": 0
},{
  "_id": {
    "$oid": "635b87c07690f94ad743c0c7"
  },
  "user": {
    "$oid": "631b2c2d4b8c7fc988a49a75"
  },
  "amount": 42,
  "paymentMethod": "card",
  "orders": [],
  "createdAt": {
    "$date": {
      "$numberLong": "1666942912840"
    }
  },
  "updatedAt": {
    "$date": {
      "$numberLong": "1666942912840"
    }
  },
  "__v": 0
},{
  "_id": {
    "$oid": "635b87f718d0e6f5b30c298c"
  },
  "user": {
    "$oid": "631b2c2d4b8c7fc988a49a75"
  },
  "amount": 42,
  "paymentMethod": "card",
  "orders": [],
  "createdAt": {
    "$date": {
      "$numberLong": "1666942967518"
    }
  },
  "updatedAt": {
    "$date": {
      "$numberLong": "1666942967518"
    }
  },
  "__v": 0
},{
  "_id": {
    "$oid": "635b8a9b1b417b9e56ae1ff2"
  },
  "user": {
    "$oid": "631b2c2d4b8c7fc988a49a73"
  },
  "amount": 42,
  "paymentMethod": "card",
  "orders": [],
  "createdAt": {
    "$date": {
      "$numberLong": "1666943643385"
    }
  },
  "updatedAt": {
    "$date": {
      "$numberLong": "1666943643385"
    }
  },
  "__v": 0
},{
  "_id": {
    "$oid": "635b8bd852d8774c24058026"
  },
  "user": {
    "$oid": "631b2c2d4b8c7fc988a49a75"
  },
  "amount": 42,
  "paymentMethod": "card",
  "orders": [],
  "createdAt": {
    "$date": {
      "$numberLong": "1666943960311"
    }
  },
  "updatedAt": {
    "$date": {
      "$numberLong": "1666943960311"
    }
  },
  "__v": 0
},{
  "_id": {
    "$oid": "635b922d20c701ce91648ca4"
  },
  "user": {
    "$oid": "631b2c2d4b8c7fc988a49a73"
  },
  "amount": 42,
  "paymentMethod": "card",
  "orders": [],
  "createdAt": {
    "$date": {
      "$numberLong": "1666945581314"
    }
  },
  "updatedAt": {
    "$date": {
      "$numberLong": "1666945581314"
    }
  },
  "__v": 0
},{
  "_id": {
    "$oid": "635b927406bf6044adac7c79"
  },
  "user": {
    "$oid": "631b2c2d4b8c7fc988a49a73"
  },
  "amount": 42,
  "paymentMethod": "card",
  "orders": [],
  "createdAt": {
    "$date": {
      "$numberLong": "1666945652153"
    }
  },
  "updatedAt": {
    "$date": {
      "$numberLong": "1666945652153"
    }
  },
  "__v": 0
},{
  "_id": {
    "$oid": "635b958f8be921c5f59a99e6"
  },
  "user": {
    "$oid": "631b2c2d4b8c7fc988a49a75"
  },
  "amount": 42,
  "paymentMethod": "card",
  "orders": [],
  "createdAt": {
    "$date": {
      "$numberLong": "1666946447943"
    }
  },
  "updatedAt": {
    "$date": {
      "$numberLong": "1666946447943"
    }
  },
  "__v": 0
},{
  "_id": {
    "$oid": "635b961d8c98621957561e43"
  },
  "user": {
    "$oid": "631b2c2d4b8c7fc988a49a75"
  },
  "amount": 42,
  "paymentMethod": "card",
  "orders": [],
  "createdAt": {
    "$date": {
      "$numberLong": "1666946589979"
    }
  },
  "updatedAt": {
    "$date": {
      "$numberLong": "1666946589980"
    }
  },
  "__v": 0
},{
  "_id": {
    "$oid": "635b9a878c98621957561e45"
  },
  "user": {
    "$oid": "631b2c2d4b8c7fc988a49a73"
  },
  "amount": 474,
  "paymentMethod": "card",
  "orders": [],
  "createdAt": {
    "$date": {
      "$numberLong": "1666947719192"
    }
  },
  "updatedAt": {
    "$date": {
      "$numberLong": "1666947719192"
    }
  },
  "__v": 0
},{
  "_id": {
    "$oid": "635b9d848c98621957561e47"
  },
  "user": {
    "$oid": "631b2c2d4b8c7fc988a49a73"
  },
  "amount": 412,
  "paymentMethod": "card",
  "orders": [],
  "createdAt": {
    "$date": {
      "$numberLong": "1666948484819"
    }
  },
  "updatedAt": {
    "$date": {
      "$numberLong": "1666948484819"
    }
  },
  "__v": 0
}]